{
  "users": [
    {
      "id": "1273314130094194750",
      "codes": [
        "DEV-SZ3A-S7IU-IP-P67I",
        "DEV-67GV-7QUA-IP-????",
        "N2X3W8",
        "DEV-4257-32AZ-IP-????",
        "DEV-4257-32AZ-IP-RKVB",
        "DEV-BXAD-KRVW-IP-EKOG",
        "DEV-4257-32AZ-IP-TFD4",
        "DEV-4257-32AZ-IP-W3WZ"
      ],
      "updated_at": "2025-08-26T06:53:34+00:00Z"
    },
    {
      "id": "1119710742308982846",
      "codes": [
        "B6K9SK",
        "CN4S4S",
        "9RWTO9",
        "48NAKY",
        "9WAAAQ",
        "DEV-7JYE-QPYV-IP-????",
        "DEV-7JYE-QPYV-IP-N4AL",
        "DEV-G42Z-EA6X-IP-N4AL",
        "DEV-JKCR-Z6PV-IP-N4AL"
      ],
      "updated_at": "2025-08-26T12:00:53+00:00Z"
    },
    {
      "id": "814824645656051723",
      "codes": [
        "U8VVUB",
        "GA5HKW",
        "DEV-YB4N-UNTN-IP-PJ63",
        "DEV-TCJD-H724-IP-PJ63",
        "DEV-P7FN-UCR6-IP-PJ63"
      ],
      "updated_at": "2025-08-28T08:01:26+00:00Z"
    },
    {
      "id": "797177241258819634",
      "codes": [
        "XF5KUV",
        "XWABB5",
        "DEV-NIMB-VRRG-IP-????",
        "DEV-4H47-L3NH-IP-NJB4",
        "DEV-4H47-L3NH-IP-3WUD",
        "DEV-4H47-L3NH-IP-JXRU"
      ],
      "updated_at": "2025-08-25T10:57:58+00:00Z"
    },
    {
      "id": "1371481584204648589",
      "codes": [
        "DEV-T7YF-JL26-IP-6OJJ",
        "DEV-N3G6-BYCH-IP-6AOD",
        "DEV-N3G6-BYCH-IP-YM2F",
        "0CJOPW",
        "DEV-T7YF-JL26-IP-YM2F",
        "DEV-T7YF-JL26-IP-XI3P",
        "RSKQBU"
      ],
      "updated_at": "2025-08-25T15:01:05+00:00Z"
    },
    {
      "id": "1012637347508146197",
      "codes": [
        "AH4M0V",
        "OUGCR8",
        "XCAFWA",
        "DEV-7BLM-64WF-IP-????",
        "DEV-7BLM-64WF-IP-CB3U",
        "DEV-7BLM-64W F-IP-CBЗU",
        "DEV-7BLM-64WF-IP-W7LP",
        "DEV-7BLM-64WF-IP-YQSQ"
      ],
      "updated_at": "2025-08-27T06:50:55+00:00Z"
    },
    {
      "id": "1267625923356786688",
      "codes": [
        "DEV-CH5P-OXIG-IP-XTBZ",
        "DEV-JH6M-L2WM-IP-????",
        "DEV-JH6M-L2WM-IP-XTBZ",
        "DEV-QZZM-PF3T-IP-XTBZ"
      ],
      "updated_at": "2025-08-28T09:56:22+00:00Z"
    },
    {
      "id": "429518788027744257",
      "codes": [
        "DEV-YCNW-WOY4-IP-????",
        "8PWHCZ",
        "DEV-YCNW-WOY4-IP-M56O",
        "DEV-ZJUC-P4UO-IP-M56O"
      ],
      "updated_at": "2025-08-25T00:39:09+00:00Z"
    },
    {
      "id": "1336984912766697514",
      "codes": [
        "J750F3",
        "DEV-KKIN-4BC4-IP-LK7L",
        "DEV-KKIN-4BC4-IP-HJ5I",
        "DEV-KKIN-4BC4-IP-MMSX",
        "DEV-KKIN-4BC4-IP-RIEE"
      ],
      "updated_at": "2025-08-24T22:24:59+00:00Z"
    },
    {
      "id": "1153179266893234208",
      "codes": [
        "DEV-MV2T-6CKN-IP-????",
        "DEV-MV2T-6CKN-IP-AZFD",
        "DEV-OV7J-2OOT-IP-AZFD",
        "DEV-PBBN-3ZJQ-IP-AZFD"
      ],
      "updated_at": "2025-08-27T02:19:47+00:00Z"
    },
    {
      "id": "956522716360474634",
      "codes": [
        "O8ROZT",
        "AW6TXU",
        "DEV-AS5M-TXON-IP-UERZ",
        "DEV-UVRS-BYTH-IP-????",
        "DEV-UVRS-BYTH-IP-UERZ",
        "DEV-2NOB-X2AC-IP-UERZ"
      ],
      "updated_at": "2025-08-24T19:21:53+00:00Z"
    },
    {
      "id": "1320720383288021062",
      "codes": [
        "PMG3PZ",
        "DEV-M2EL-WFZ5-IP-CGZA",
        "DEV-EV3T-6CPA-IP-CGZA"
      ],
      "updated_at": "2025-08-26T02:31:42+00:00Z"
    },
    {
      "id": "1028961300723814400",
      "codes": [
        "test",
        "DEV-DJJA-ILKG-IP-XI3P",
        "DEV-DJJA-ILKG-IP-HOMX"
      ],
      "updated_at": "2025-08-25T21:38:24+00:00Z"
    },
    {
      "id": "988045396825763940",
      "codes": [
        "32JJQV",
        "52XGSE",
        "WOA9S5",
        "DEV-5F6C-B2YM-IP-ESH7"
      ],
      "updated_at": "2025-08-25T04:29:40+00:00Z"
    },
    {
      "id": "1243835003293401128",
      "codes": [
        "DEV-NGV5-SSXO-IP-????",
        "DEV-NGV5-SSX0-TKR7",
        "DEV-NGV5-SSXO-IP-TKR7"
      ],
      "updated_at": "2025-08-23T07:38:31+00:00Z"
    },
    {
      "id": "1279284152516218932",
      "codes": [
        "DEV-VNY5-JSJV-IP-CPWI",
        "DEV-VNY5-JSJV-IP-3AA7",
        "DEV-VNY5-JSJV-IP-7O62",
        "QWMOCD"
      ],
      "updated_at": "2025-08-28T07:25:32+00:00Z"
    },
    {
      "id": "1198631357954392216",
      "codes": [
        "DEV-4Z37-7OOQ-IP-????",
        "DEV-4Z37-7OOQ-IP-75EP"
      ],
      "updated_at": "2025-08-24T16:45:09+00:00Z"
    },
    {
      "id": "1278896725314109452",
      "codes": [
        "DEV-EW3G-DFCN-IP-XUWD",
        "DEV-EW3G-DFCN-IP-EYZS",
        "DEV-EW3G-DFCN-IP-????",
        "DEV-EW3G-DFCN-IP-Z35G",
        "DEV-EW3G-DFCN-IP-ZNPI",
        "DEV-EW3G-DFCN-IP-SOP7",
        "DEV-LAQQ-Q6M2-IP-????",
        "DEV-LAQQ-Q6M2-IP-SOP7",
        "DEV-WQXH-QWAK-IP-SOP7",
        "DEV-WQXH-QWAK-IP-????"
      ],
      "updated_at": "2025-08-27T04:44:26+00:00Z"
    },
    {
      "id": "1350515975723814952",
      "codes": [
        "8TVSQF",
        "K8M5DO",
        "WD2Y4Z",
        "DEV-BUDI-CKQ5-IP-FTQ5"
      ],
      "updated_at": "2025-08-26T14:14:17+00:00Z"
    },
    {
      "id": "1098933467024212070",
      "codes": [
        "W4ERBN",
        "DEV-HK32-NADZ-IP-LQNQ",
        "DEV-PBSO-UQDI-IP-MFHS",
        "DEV-HK32-NADZ-IP-????",
        "DEV-HK32-NADZ-IP-PRFM",
        "DEV-PBSO-UQDI-IP-35K2",
        "DEV-THUQ-RTI6-IP-HGDF",
        "DEV-PBSO-UQDI-IP-XR4X",
        "DEV-PBSO-UQDI-IP-27KX",
        "DEV-PBSO-UQDI-IP-UMDO"
      ],
      "updated_at": "2025-08-25T23:25:26+00:00Z"
    },
    {
      "id": "1097102677923614730",
      "codes": [
        "DEV-24SD-NKE5-????",
        "DEV-24SD-NKE5-UJ23",
        "DEV-24SD-NKE5-IP-UJ23"
      ],
      "updated_at": "2025-08-24T03:23:54+00:00Z"
    },
    {
      "id": "1231138075187351624",
      "codes": [
        "DEV-HY47-2I2P-IP-????",
        "DEV-BDON-2JBB-IP-SW46",
        "DEV-QNQF-VJXP-IP-SW46",
        "DEV-HY47-2I2P-IP-SW46"
      ],
      "updated_at": "2025-08-25T08:15:21+00:00Z"
    },
    {
      "id": "863393545204531210",
      "codes": [
        "DEV-Q4DX-7GD4-IP-????",
        "DEV-Q4DX-7GD4-IP-U7AW",
        "DEV-IIGW-OMVO-IP-U7AW"
      ],
      "updated_at": "2025-08-27T10:48:03+00:00Z"
    },
    {
      "id": "845310702515781632",
      "codes": [
        "2P4GKR",
        "A4RYF2"
      ],
      "updated_at": "2025-08-24T14:04:53+00:00Z"
    },
    {
      "id": "643748450248294411",
      "codes": [
        "DEV-EFF",
        "DEV-EFFA-VQMP-IP-????",
        "DEV-EFFA-VQMP-IP-PNPD",
        "DEV-UUU2-TGVN-IP-PNPD"
      ],
      "updated_at": "2025-08-24T20:28:31+00:00Z"
    },
    {
      "id": "795541669571067904",
      "codes": [
        "DEV-GZ5H-RM7G-IP-????",
        "DEV-GZ5H-RM7G-IP-SZ3E"
      ],
      "updated_at": "2025-08-24T17:51:11+00:00Z"
    },
    {
      "id": "721558311635255305",
      "codes": [
        "ｇｄｓｃｈ",
        "DEV-YXJ5-B4MZ-IP-????",
        "DEV-YXJ5-B4MZ-IP-VKGW",
        "DEV-YXJ5-B4MZ-IP-XS6P",
        "DEV-YXJ5-B4MZ-IP-MDWB",
        "DEV-YXJ5-B4MZ-IP-FTFN",
        "DEV-YXJ5-B4MZ-IP-XQBW"
      ],
      "updated_at": "2025-08-26T13:38:51+00:00Z"
    },
    {
      "id": "1244927139640508507",
      "codes": [
        "DEV-3DWZ-MRHG-IP-THWS",
        "DEV-PNKT-NRA6-IP-THWS",
        "DEV-PNKT-NRA6-IP-????"
      ],
      "updated_at": "2025-08-25T10:55:12+00:00Z"
    },
    {
      "id": "980695090819387443",
      "codes": [
        "DEV-7GQH-TQXR-IP-1220",
        "DEV-7GQH-TQXR-IP-????",
        "DEV-5MOM-HDSZ-IP-????",
        "DEV-5MOM-HDSZ-IP-N7ZH",
        "DEV-7GQH-TQXR-IP-N7ZH"
      ],
      "updated_at": "2025-08-25T11:56:08+00:00Z"
    },
    {
      "id": "796709095150321744",
      "codes": [
        "DEV-7G2C-KO56-IP-QNGT"
      ],
      "updated_at": "2025-08-25T12:02:49+00:00Z"
    },
    {
      "id": "1134328426728263680",
      "codes": [
        "DEV-UTGH-LVK2-IP-????",
        "DEV-UTGH-LVK2-IP-GENI"
      ],
      "updated_at": "2025-08-25T12:39:48+00:00Z"
    },
    {
      "id": "1356942870933671997",
      "codes": [
        "DEV-IIUO-EZCV-IP-2S2Q",
        "DEV-6NPS-CTF5-IP-FHVJ"
      ],
      "updated_at": "2025-08-26T01:22:28+00:00Z"
    },
    {
      "id": "1379051307209330751",
      "codes": [
        "DEV-A7EW-DKKS-IP-JXDW"
      ],
      "updated_at": "2025-08-26T03:58:11+00:00Z"
    },
    {
      "id": "825881509004181576",
      "codes": [
        "DEV-ROXL-V3YJ-IP-????",
        "DEV-SCQ7-CB6N-IP-UE72",
        "DEV-ROXL-V3YJ-IP-UE72"
      ],
      "updated_at": "2025-08-27T14:26:10+00:00Z"
    },
    {
      "id": "1397241683997102122",
      "codes": [
        "MT02"
      ],
      "updated_at": "2025-08-28T07:12:10+00:00Z"
    },
    {
      "id": "1103486448436531342",
      "codes": [
        "DEV-HQFB-YBRE-IP-????",
        "DEV-HQFB-YBRE-IP-ZHLY"
      ],
      "updated_at": "2025-08-28T09:08:42+00:00Z"
    },
    {
      "id": "843439491477667880",
      "codes": [
        "DEV-BOUN-JDWG-IP-????",
        "DEV-BOUN-JDWG-IP-RNXU"
      ],
      "updated_at": "2025-08-28T09:29:21+00:00Z"
    },
    {
      "id": "991302390915551253",
      "codes": [
        "DEV-3M6O-2DNR-IP-????"
      ],
      "updated_at": "2025-08-28T12:00:03+00:00Z"
    }
  ],
  "codes": [
    "DEV-SZ3A-S7IU-IP-P67I",
    "B6K9SK",
    "CN4S4S",
    "U8VVUB",
    "XF5KUV",
    "XWABB5",
    "DEV-T7YF-JL26-IP-6OJJ",
    "AH4M0V",
    "DEV-YCNW-WOY4-IP-????",
    "8PWHCZ",
    "J750F3",
    "DEV-KKIN-4BC4-IP-LK7L",
    "DEV-YCNW-WOY4-IP-M56O",
    "DEV-KKIN-4BC4-IP-HJ5I",
    "DEV-MV2T-6CKN-IP-????",
    "DEV-MV2T-6CKN-IP-AZFD",
    "DEV-KKIN-4BC4-IP-MMSX",
    "O8ROZT",
    "AW6TXU",
    "PMG3PZ",
    "9RWTO9",
    "48NAKY",
    "9WAAAQ",
    "42D6MM",
    "32JJQV",
    "DEV-NGV5-SSXO-IP-????",
    "DEV-NGV5-SSX0-TKR7",
    "DEV-NGV5-SSXO-IP-TKR7",
    "DEV-VNY5-JSJV-IP-CPWI",
    "OUGCR8",
    "XCAFWA",
    "52XGSE",
    "WOA9S5",
    "DEV-NIMB-VRRG-IP-????",
    "DEV-N3G6-BYCH-IP-6AOD",
    "DEV-67GV-7QUA-IP-????",
    "DEV-4Z37-7OOQ-IP-????",
    "DEV-EW3G-DFCN-IP-XUWD",
    "8TVSQF",
    "K8M5DO",
    "WD2Y4Z",
    "W4ERBN",
    "29E1XY",
    "0BCMKN",
    "DEV-24SD-NKE5-????",
    "DEV-24SD-NKE5-UJ23",
    "DEV-24SD-NKE5-IP-UJ23",
    "DEV-EW3G-DFCN-IP-EYZS",
    "DEV-EW3G-DFCN-IP-????",
    "DEV-N3G6-BYCH-IP-YM2F",
    "0CJOPW",
    "DEV-T7YF-JL26-IP-YM2F",
    "DEV-T7YF-JL26-IP-XI3P",
    "DEV-HY47-2I2P-IP-????",
    "9CPNTP",
    "Z12QYS",
    "DEV-BDON-2JBB-IP-SW46",
    "9B9JDO",
    "9B9JD0",
    "DEV-EW3G-DFCN-IP-Z35G",
    "DEV-Q4DX-7GD4-IP-????",
    "DEV-Q4DX-7GD4-IP-U7AW",
    "2P4GKR",
    "A4RYF2",
    "DEV-OV7J-2OOT-IP-AZFD",
    "N2X3W8",
    "DEV-EFF",
    "DEV-EFFA-VQMP-IP-????",
    "DEV-EFFA-VQMP-IP-PNPD",
    "DEV-4H47-L3NH-IP-NJB4",
    "DEV-CH5P-OXIG-IP-XTBZ",
    "DEV-4Z37-7OOQ-IP-75EP",
    "DEV-QNQF-VJXP-IP-SW46",
    "DEV-GZ5H-RM7G-IP-????",
    "DEV-GZ5H-RM7G-IP-SZ3E",
    "DEV-AS5M-TXON-IP-UERZ",
    "DEV-UVRS-BYTH-IP-????",
    "DEV-UVRS-BYTH-IP-UERZ",
    "DEV-2NOB-X2AC-IP-UERZ",
    "DEV-HK32-NADZ-IP-LQNQ",
    "DEV-UUU2-TGVN-IP-PNPD",
    "DEV-PBSO-UQDI-IP-MFHS",
    "DEV-YHZF-N3SJ-IP-IWIT",
    "DEV-YHZF-N3SJ-IP-J7RL",
    "DEV-KKIN-4BC4-IP-RIEE",
    "DEV-HK32-NADZ-IP-????",
    "DEV-HK32-NADZ-IP-PRFM",
    "DEV-PBSO-UQDI-IP-35K2",
    "GA5HKW",
    "DEV-ZJUC-P4UO-IP-M56O",
    "DEV-4H47-L3NH-IP-3WUD",
    "DEV-M2EL-WFZ5-IP-CGZA",
    "DEV-5F6C-B2YM-IP-ESH7",
    "DEV-THUQ-RTI6-IP-HGDF",
    "DEV-7JYE-QPYV-IP-????",
    "DEV-7JYE-QPYV-IP-N4AL",
    "DEV-G42Z-EA6X-IP-N4AL",
    "ｇｄｓｃｈ",
    "DEV-YXJ5-B4MZ-IP-????",
    "DEV-YXJ5-B4MZ-IP-VKGW",
    "DEV-HY47-2I2P-IP-SW46",
    "DEV-7BLM-64WF-IP-????",
    "DEV-7BLM-64WF-IP-CB3U",
    "DEV-7BLM-64W F-IP-CBЗU",
    "DEV-7BLM-64WF-IP-W7LP",
    "DEV-DJJA-ILKG-IP-XI3P",
    "DEV-4257-32AZ-IP-????",
    "DEV-4257-32AZ-IP-RKVB",
    "DEV-3DWZ-MRHG-IP-THWS",
    "DEV-PNKT-NRA6-IP-THWS",
    "DEV-PNKT-NRA6-IP-????",
    "DEV-4H47-L3NH-IP-JXRU",
    "DEV-YB4N-UNTN-IP-PJ63",
    "DEV-TCJD-H724-IP-PJ63",
    "DEV-7GQH-TQXR-IP-1220",
    "DEV-7GQH-TQXR-IP-????",
    "DEV-5MOM-HDSZ-IP-????",
    "DEV-5MOM-HDSZ-IP-N7ZH",
    "DEV-7GQH-TQXR-IP-N7ZH",
    "DEV-7G2C-KO56-IP-QNGT",
    "DEV-UTGH-LVK2-IP-????",
    "DEV-UTGH-LVK2-IP-GENI",
    "DEV-YXJ5-B4MZ-IP-XS6P",
    "DEV-YXJ5-B4MZ-IP-MDWB",
    "DEV-EW3G-DFCN-IP-ZNPI",
    "RSKQBU",
    "DEV-JH6M-L2WM-IP-????",
    "DEV-JH6M-L2WM-IP-XTBZ",
    "DEV-YXJ5-B4MZ-IP-FTFN",
    "DEV-PBSO-UQDI-IP-XR4X",
    "DEV-PBSO-UQDI-IP-27KX",
    "DEV-DJJA-ILKG-IP-HOMX",
    "DEV-PBSO-UQDI-IP-UMDO",
    "DEV-IIUO-EZCV-IP-2S2Q",
    "DEV-6NPS-CTF5-IP-FHVJ",
    "DEV-EV3T-6CPA-IP-CGZA",
    "DEV-BXAD-KRVW-IP-EKOG",
    "DEV-A7EW-DKKS-IP-JXDW",
    "DEV-4257-32AZ-IP-TFD4",
    "DEV-4257-32AZ-IP-W3WZ",
    "DEV-JKCR-Z6PV-IP-N4AL",
    "DEV-EW3G-DFCN-IP-SOP7",
    "DEV-LAQQ-Q6M2-IP-????",
    "DEV-LAQQ-Q6M2-IP-SOP7",
    "DEV-YXJ5-B4MZ-IP-XQBW",
    "DEV-BUDI-CKQ5-IP-FTQ5",
    "DEV-PBBN-3ZJQ-IP-AZFD",
    "DEV-WQXH-QWAK-IP-SOP7",
    "DEV-WQXH-QWAK-IP-????",
    "DEV-7BLM-64WF-IP-YQSQ",
    "DEV-IIGW-OMVO-IP-U7AW",
    "DEV-ROXL-V3YJ-IP-????",
    "DEV-SCQ7-CB6N-IP-UE72",
    "DEV-ROXL-V3YJ-IP-UE72",
    "DEV-VNY5-JSJV-IP-3AA7",
    "DEV-VNY5-JSJV-IP-7O62",
    "MT02",
    "QWMOCD",
    "DEV-P7FN-UCR6-IP-PJ63",
    "DEV-HQFB-YBRE-IP-????",
    "DEV-HQFB-YBRE-IP-ZHLY",
    "DEV-BOUN-JDWG-IP-????",
    "DEV-BOUN-JDWG-IP-RNXU",
    "DEV-QZZM-PF3T-IP-XTBZ",
    "DEV-3M6O-2DNR-IP-????"
  ]
}